environpy/__init__.py
environpy/dev.py
environpy/dev_.py
environpy/environshell.py
environ_py-0.0.9.dist-info/METADATA
environ_py-0.0.9.dist-info/WHEEL
environ_py-0.0.9.dist-info/licenses/LICENSE
environ_py-0.0.9.dist-info/RECORD
