Metadata-Version: 2.1
Name: Environ-Py
Version: 0.0.9
Summary: A Package made for you to make your project even BETTER! (VERSION 0.0.9 OUT!)
Project-URL: Homepage, https://github.com/OpenStudioX/Environ
Project-URL: Bug Tracker, https://github.com/OpenStudioX/Environ/issues/choose
Project-URL: Examples, https://github.com/OpenStudioX/Environ/tree/main/examples
Project-URL: Guide, https://github.com/OpenStudioX2/Environ/wiki/guide
Author: Rayaan khan
License-File: LICENSE
Classifier: License :: OSI Approved :: MIT License
Classifier: Operating System :: OS Independent
Classifier: Programming Language :: Python :: 3
Requires-Python: >=3.8
Requires-Dist: pycolortools==0.0.2
